[
	[
		{
			"id": "53680",
			"title": "星期六女鞋专场",
			"watchword": "",
			"image": "http://i.okaybuy.cn/images/multipic/new/201612/5f/5f9c60c17f0566aaa4e623b509274af6.jpg",
			"slogan": "靓丽舒适美鞋",
			"discount": "下单立减50元",
			"discount_word": "",
			"starttime": "12/26/2016 10:00:00",
			"endtime": "12/30/2016 09:59:59",
			"nowtime": "12/29/2016 17:50:41",
			"link": "/outlets/show/53680",
			"isnew": 0,
			"islastday": 1,
			"pic_word": "12月26日-12月30日",
			"pic_wordstart": "12月26日"
		}, {
			"id": "53689",
			"title": "Hardly Ever\\'s专场",
			"watchword": "",
			"image": "http://i.okaybuy.cn/images/multipic/new/201612/6b/6bea6714ceb566ea5f5a8267e6c1c16a.jpg",
			"slogan": "时尚出型",
			"discount": "折上7.5折",
			"discount_word": "",
			"starttime": "12/26/2016 10:00:00",
			"endtime": "01/02/2017 09:59:59",
			"nowtime": "12/29/2016 17:50:41",
			"link": "/outlets/show/53689",
			"isnew": 0,
			"islastday": 0,
			"pic_word": "12月26日-01月02日",
			"pic_wordstart": "12月26日"
		}, {
			"id": "53712",
			"title": "cottonpop专场",
			"watchword": "",
			"image": "http://i.okaybuy.cn/images/multipic/new/201612/bd/bd5755165ae9762e83b8be7e70c04a45.jpg",
			"slogan": "舒适棉袜",
			"discount": "12元起",
			"discount_word": "",
			"starttime": "12/26/2016 10:00:00",
			"endtime": "01/02/2017 09:59:59",
			"nowtime": "12/29/2016 17:50:41",
			"link": "/outlets/show/53712",
			"isnew": 0,
			"islastday": 0,
			"pic_word": "12月26日-01月02日",
			"pic_wordstart": "12月26日"
		}, {
			"id": "53692",
			"title": "swisswin专场",
			"watchword": "",
			"image": "http://i.okaybuy.cn/images/multipic/new/201612/53/53781afcc4d944b988a22ed315b84c8c.jpg",
			"slogan": "品质背包",
			"discount": "68元起",
			"discount_word": "",
			"starttime": "12/26/2016 10:00:00",
			"endtime": "01/02/2017 09:59:59",
			"nowtime": "12/29/2016 17:50:41",
			"link": "/outlets/show/53692",
			"isnew": 0,
			"islastday": 0,
			"pic_word": "12月26日-01月02日",
			"pic_wordstart": "12月26日"
		}, {
			"id": "53693",
			"title": "迪士尼&小熊维尼专场",
			"watchword": "满129元减10元 满199元减30元 满359元减50元",
			"image": "http://i.okaybuy.cn/images/multipic/new/201612/40/408b5d7fae7c76efe43b02b01ceb90a9.jpg",
			"slogan": "精品童鞋",
			"discount": "满359元减50",
			"discount_word": "",
			"starttime": "12/26/2016 10:00:00",
			"endtime": "01/02/2017 09:59:59",
			"nowtime": "12/29/2016 17:50:41",
			"link": "/outlets/show/53693",
			"isnew": 0,
			"islastday": 0,
			"pic_word": "12月26日-01月02日",
			"pic_wordstart": "12月26日"
		}, {
			"id": "53688",
			"title": "顶呱呱专场",
			"watchword": "满99减10元",
			"image": "http://i.okaybuy.cn/images/multipic/new/201612/45/45d59a52d0c1d087188c14f865dd3739.jpg",
			"slogan": "舒适 休闲 经典",
			"discount": "满99减10元",
			"discount_word": "",
			"starttime": "12/26/2016 10:00:00",
			"endtime": "01/02/2017 09:59:59",
			"nowtime": "12/29/2016 17:50:41",
			"link": "/outlets/show/53688",
			"isnew": 0,
			"islastday": 0,
			"pic_word": "12月26日-01月02日",
			"pic_wordstart": "12月26日"
		}, {
			"id": "53696",
			"title": "爱乐专场",
			"watchword": "",
			"image": "http://i.okaybuy.cn/images/multipic/new/201612/f4/f4598aee5cb8adc934d50eea1fabaf8a.jpg",
			"slogan": "休闲经典鞋",
			"discount": "299两双任意搭",
			"discount_word": "",
			"starttime": "12/26/2016 10:00:00",
			"endtime": "12/30/2016 09:59:59",
			"nowtime": "12/29/2016 17:50:41",
			"link": "/outlets/show/53696",
			"isnew": 0,
			"islastday": 1,
			"pic_word": "12月26日-12月30日",
			"pic_wordstart": "12月26日"
		}, {
			"id": "53705",
			"title": "范斯蒂克专场",
			"watchword": "",
			"image": "http://i.okaybuy.cn/images/multipic/new/201612/59/5963d864e687b29cec7dcfdf8a7b1c08.jpg",
			"slogan": "运动专业品质",
			"discount": "39元起",
			"discount_word": "",
			"starttime": "12/25/2016 10:00:00",
			"endtime": "01/01/2017 09:59:59",
			"nowtime": "12/29/2016 17:50:41",
			"link": "/outlets/show/53705",
			"isnew": 0,
			"islastday": 0,
			"pic_word": "12月25日-01月01日",
			"pic_wordstart": "12月25日"
		}, {
			"id": "53711",
			"title": "童鞋专场",
			"watchword": "",
			"image": "http://i.okaybuy.cn/images/multipic/new/201612/31/3101ef749ec38a7963e59bf1f4e2102f.jpg",
			"slogan": "精品童鞋",
			"discount": "3折起",
			"discount_word": "",
			"starttime": "12/25/2016 10:00:00",
			"endtime": "01/01/2017 09:59:59",
			"nowtime": "12/29/2016 17:50:41",
			"link": "/outlets/show/53711",
			"isnew": 0,
			"islastday": 0,
			"pic_word": "12月25日-01月01日",
			"pic_wordstart": "12月25日"
		}, {
			"id": "53708",
			"title": "童装专场",
			"watchword": "",
			"image": "http://i.okaybuy.cn/images/multipic/new/201611/ca/cada3818e406dd6a557fcfc0230b4092.jpg",
			"slogan": "精品童装",
			"discount": "3折起",
			"discount_word": "",
			"starttime": "12/25/2016 10:00:00",
			"endtime": "01/01/2017 09:59:59",
			"nowtime": "12/29/2016 17:50:41",
			"link": "/outlets/show/53708",
			"isnew": 0,
			"islastday": 0,
			"pic_word": "12月25日-01月01日",
			"pic_wordstart": "12月25日"
		}, {
			"id": "53709",
			"title": "运动内衣综合专场",
			"watchword": "",
			"image": "http://i.okaybuy.cn/images/multipic/new/201612/4a/4afd8460a7d2cdecd14c365f75854ab7.jpg",
			"slogan": "运动专业品质",
			"discount": "1件9折 2件8折",
			"discount_word": "",
			"starttime": "12/25/2016 10:00:00",
			"endtime": "01/01/2017 09:59:59",
			"nowtime": "12/29/2016 17:50:41",
			"link": "/outlets/show/53709",
			"isnew": 0,
			"islastday": 0,
			"pic_word": "12月25日-01月01日",
			"pic_wordstart": "12月25日"
		}, {
			"id": "53566",
			"title": "波斯丹顿专场",
			"watchword": "",
			"image": "http://i.okaybuy.cn/images/multipic/new/201612/16/16439b4d184728877e5f1fa808026603.jpg",
			"slogan": "时尚背包",
			"discount": "99元减10 上不封顶",
			"discount_word": "",
			"starttime": "12/25/2016 10:00:00",
			"endtime": "01/01/2017 09:59:59",
			"nowtime": "12/29/2016 17:50:41",
			"link": "/outlets/show/53566",
			"isnew": 0,
			"islastday": 0,
			"pic_word": "12月25日-01月01日",
			"pic_wordstart": "12月25日"
		}
	],
	[
		{
			"id": "53888",
			"title": "耐克运动鞋专场",
			"watchword": "",
			"image": "http://i.okaybuy.cn/images/multipic/new/201612/db/db4da98ac39e7634450081b5e14f004c.jpg",
			"slogan": "时尚运动 释放自我",
			"discount": "149元起",
			"discount_word": "",
			"starttime": "12/29/2016 10:00:00",
			"endtime": "01/03/2017 09:59:59",
			"nowtime": "12/29/2016 21:47:18",
			"link": "/outlets/show/53888",
			"isnew": 1,
			"islastday": 0,
			"pic_word": "12月29日-01月03日",
			"pic_wordstart": "12月29日"
		}, {
			"id": "53926",
			"title": "阿迪达斯运动鞋专场",
			"watchword": "",
			"image": "http://i.okaybuy.cn/images/multipic/new/201612/b1/b1df71edf99c12bfd84ec2b666913b34.jpg",
			"slogan": "没有不可能",
			"discount": "169元起",
			"discount_word": "",
			"starttime": "12/29/2016 10:00:00",
			"endtime": "01/03/2017 09:59:59",
			"nowtime": "12/29/2016 21:47:18",
			"link": "/outlets/show/53926",
			"isnew": 1,
			"islastday": 0,
			"pic_word": "12月29日-01月03日",
			"pic_wordstart": "12月29日"
		}, {
			"id": "53896",
			"title": "李宁运动鞋专场",
			"watchword": "",
			"image": "http://i.okaybuy.cn/images/multipic/new/201612/89/893e2b7c6643eb4db194074b08673914.jpg",
			"slogan": "一切皆有可能",
			"discount": "18元起",
			"discount_word": "",
			"starttime": "12/29/2016 10:00:00",
			"endtime": "01/03/2017 09:59:59",
			"nowtime": "12/29/2016 21:47:18",
			"link": "/outlets/show/53896",
			"isnew": 1,
			"islastday": 0,
			"pic_word": "12月29日-01月03日",
			"pic_wordstart": "12月29日"
		}, {
			"id": "53913",
			"title": "安踏运动鞋专场",
			"watchword": "",
			"image": "http://i.okaybuy.cn/images/multipic/new/201612/7d/7d1c814de167dd5bab9ef37de04384e4.jpg",
			"slogan": "科学设计 经典舒适",
			"discount": "69元起",
			"discount_word": "",
			"starttime": "12/29/2016 10:00:00",
			"endtime": "01/03/2017 09:59:59",
			"nowtime": "12/29/2016 21:47:18",
			"link": "/outlets/show/53913",
			"isnew": 1,
			"islastday": 0,
			"pic_word": "12月29日-01月03日",
			"pic_wordstart": "12月29日"
		}, {
			"id": "53861",
			"title": "新百伦专场",
			"watchword": "",
			"image": "http://i.okaybuy.cn/images/multipic/new/201612/79/79c3c4c4d7376eb81dc621de2632bd4b.jpg",
			"slogan": "青春不褪色",
			"discount": "169元起",
			"discount_word": "",
			"starttime": "12/29/2016 10:00:00",
			"endtime": "01/03/2017 09:59:59",
			"nowtime": "12/29/2016 21:47:18",
			"link": "/outlets/show/53861",
			"isnew": 1,
			"islastday": 0,
			"pic_word": "12月29日-01月03日",
			"pic_wordstart": "12月29日"
		}, {
			"id": "53862",
			"title": "匡威专场",
			"watchword": "",
			"image": "http://i.okaybuy.cn/images/multipic/new/201612/10/10e5b124de6292cd70aa1e7629a5fdb5.jpg",
			"slogan": "极简新经典",
			"discount": "19元起",
			"discount_word": "",
			"starttime": "12/29/2016 10:00:00",
			"endtime": "01/03/2017 09:59:59",
			"nowtime": "12/29/2016 21:47:18",
			"link": "/outlets/show/53862",
			"isnew": 1,
			"islastday": 0,
			"pic_word": "12月29日-01月03日",
			"pic_wordstart": "12月29日"
		}, {
			"id": "53899",
			"title": "复古鞋专场",
			"watchword": "",
			"image": "http://i.okaybuy.cn/images/multipic/new/201612/2e/2e8222092596db70ef0fd28dcefb28f1.jpg",
			"slogan": "舒适 休闲 经典",
			"discount": "211元起",
			"discount_word": "",
			"starttime": "12/29/2016 10:00:00",
			"endtime": "01/03/2017 09:59:59",
			"nowtime": "12/29/2016 21:47:18",
			"link": "/outlets/show/53899",
			"isnew": 1,
			"islastday": 0,
			"pic_word": "12月29日-01月03日",
			"pic_wordstart": "12月29日"
		}, {
			"id": "53724",
			"title": "骆驼品牌专场",
			"watchword": "2双再减50",
			"image": "http://i.okaybuy.cn/images/multipic/new/201612/ea/ea9bf849062c39e794f981470e3d3c46.jpg",
			"slogan": "年末清仓特惠",
			"discount": "2双再减50",
			"discount_word": "",
			"starttime": "12/29/2016 10:00:01",
			"endtime": "01/03/2017 09:59:59",
			"nowtime": "12/29/2016 21:47:18",
			"link": "/outlets/show/53724",
			"isnew": 1,
			"islastday": 0,
			"pic_word": "12月29日-01月03日",
			"pic_wordstart": "12月29日"
		}
	]
	,
	[
		{
			"id": "53891",
			"title": "耐克运动服专场",
			"watchword": "",
			"image": "http://i.okaybuy.cn/images/multipic/new/201612/34/3453d099a96a02a1c8884a993bdbf49a.jpg",
			"slogan": "JUST DO IT",
			"discount": "69元起",
			"discount_word": "",
			"starttime": "12/29/2016 10:00:00",
			"endtime": "01/03/2017 09:59:59",
			"nowtime": "12/29/2016 21:49:04",
			"link": "/outlets/show/53891",
			"isnew": 1,
			"islastday": 0,
			"pic_word": "12月29日-01月03日",
			"pic_wordstart": "12月29日"
		}, {
			"id": "53925",
			"title": "阿迪达斯运动服专场",
			"watchword": "",
			"image": "http://i.okaybuy.cn/images/multipic/new/201612/b1/b17bdba29460d43a3fbba8870fff03bc.jpg",
			"slogan": "练上冬季",
			"discount": "49元起",
			"discount_word": "",
			"starttime": "12/29/2016 10:00:00",
			"endtime": "01/03/2017 09:59:59",
			"nowtime": "12/29/2016 21:49:04",
			"link": "/outlets/show/53925",
			"isnew": 1,
			"islastday": 0,
			"pic_word": "12月29日-01月03日",
			"pic_wordstart": "12月29日"
		}, {
			"id": "53897",
			"title": "李宁服装专场",
			"watchword": "",
			"image": "http://i.okaybuy.cn/images/multipic/new/201612/0e/0e58c18efb14d691fcb4d38ad51802fc.jpg",
			"slogan": "轻装上阵 越冬越动",
			"discount": "19元起",
			"discount_word": "",
			"starttime": "12/29/2016 10:00:00",
			"endtime": "01/03/2017 09:59:59",
			"nowtime": "12/29/2016 21:49:04",
			"link": "/outlets/show/53897",
			"isnew": 1,
			"islastday": 0,
			"pic_word": "12月29日-01月03日",
			"pic_wordstart": "12月29日"
		}, {
			"id": "53914",
			"title": "安踏运动服",
			"watchword": "",
			"image": "http://i.okaybuy.cn/images/multipic/new/201612/4a/4a1462b69d1c48b6e1c41bed76ec706d.jpg",
			"slogan": "温暖出型",
			"discount": "低至2折",
			"discount_word": "",
			"starttime": "12/29/2016 10:00:00",
			"endtime": "01/03/2017 09:59:59",
			"nowtime": "12/29/2016 21:49:04",
			"link": "/outlets/show/53914",
			"isnew": 1,
			"islastday": 0,
			"pic_word": "12月29日-01月03日",
			"pic_wordstart": "12月29日"
		}, {
			"id": "53898",
			"title": "kappa专场",
			"watchword": "",
			"image": "http://i.okaybuy.cn/images/multipic/new/201612/f4/f4027f661503cbc3bb84b92858198829.jpg",
			"slogan": "冬季运动不停歇",
			"discount": "19元起",
			"discount_word": "",
			"starttime": "12/29/2016 10:00:00",
			"endtime": "01/03/2017 09:59:59",
			"nowtime": "12/29/2016 21:49:04",
			"link": "/outlets/show/53898",
			"isnew": 1,
			"islastday": 0,
			"pic_word": "12月29日-01月03日",
			"pic_wordstart": "12月29日"
		}, {
			"id": "53902",
			"title": "三叶草专场",
			"watchword": "",
			"image": "http://i.okaybuy.cn/images/multipic/new/201612/3c/3c1dfd34e71d918c08938b7d38210bbb.jpg",
			"slogan": "休闲复古 尽显潮流",
			"discount": "1折起",
			"discount_word": "",
			"starttime": "12/29/2016 10:00:00",
			"endtime": "01/03/2017 09:59:59",
			"nowtime": "12/29/2016 21:49:04",
			"link": "/outlets/show/53902",
			"isnew": 1,
			"islastday": 0,
			"pic_word": "12月29日-01月03日",
			"pic_wordstart": "12月29日"
		}, {
			"id": "53929",
			"title": "NEO专场",
			"watchword": "",
			"image": "http://i.okaybuy.cn/images/multipic/new/201612/48/48b89d8605ae4a188d36bf2183f8510d.jpg",
			"slogan": "运动生活优选",
			"discount": "",
			"discount_word": "",
			"starttime": "12/29/2016 10:00:00",
			"endtime": "01/03/2017 09:59:59",
			"nowtime": "12/29/2016 21:49:04",
			"link": "/outlets/show/53929",
			"isnew": 1,
			"islastday": 0,
			"pic_word": "12月29日-01月03日",
			"pic_wordstart": "12月29日"
		}, {
			"id": "53748",
			"title": "艾格专场",
			"watchword": "",
			"image": "http://i.okaybuy.cn/images/multipic/new/201612/b9/b983fc21bf69cf595c6c2719101b51b3.jpg",
			"slogan": "冬装特惠",
			"discount": "一件8折，两件7折",
			"discount_word": "",
			"starttime": "12/27/2016 10:00:00",
			"endtime": "12/30/2016 09:59:59",
			"nowtime": "12/29/2016 21:49:04",
			"link": "/outlets/show/53748",
			"isnew": 0,
			"islastday": 1,
			"pic_word": "12月27日-12月30日",
			"pic_wordstart": "12月27日"
		}, {
			"id": "53771",
			"title": "马克华菲专场",
			"watchword": "棉羽清仓价79起！春季新品79元起！",
			"image": "http://i.okaybuy.cn/images/multipic/new/201612/0e/0e48e26ad56f0e50fa486918825ef2a1.jpg",
			"slogan": "时尚男装",
			"discount": "79元起",
			"discount_word": "",
			"starttime": "12/27/2016 10:00:00",
			"endtime": "12/30/2016 09:59:59",
			"nowtime": "12/29/2016 21:49:04",
			"link": "/outlets/show/53771",
			"isnew": 0,
			"islastday": 1,
			"pic_word": "12月27日-12月30日",
			"pic_wordstart": "12月27日"
		}, {
			"id": "53718",
			"title": "全球购年末清仓",
			"watchword": "",
			"image": "http://i.okaybuy.cn/images/multipic/new/201612/b3/b3f5fcd095564bb16fb3a720ab93f0c6.jpg",
			"slogan": "年末清仓特惠",
			"discount": "99元起",
			"discount_word": "",
			"starttime": "12/29/2016 10:00:01",
			"endtime": "01/03/2017 09:59:59",
			"nowtime": "12/29/2016 21:49:04",
			"link": "/outlets/show/53718",
			"isnew": 1,
			"islastday": 0,
			"pic_word": "12月29日-01月03日",
			"pic_wordstart": "12月29日"
		}, {
			"id": "53860",
			"title": "锐步专场",
			"watchword": "",
			"image": "http://i.okaybuy.cn/images/multipic/new/201612/a9/a9dab05716a4d235806746b2018d14c1.jpg",
			"slogan": "大胆 乐趣 振奋",
			"discount": "29元起",
			"discount_word": "",
			"starttime": "12/29/2016 10:00:00",
			"endtime": "01/03/2017 09:59:59",
			"nowtime": "12/29/2016 21:49:04",
			"link": "/outlets/show/53860",
			"isnew": 1,
			"islastday": 0,
			"pic_word": "12月29日-01月03日",
			"pic_wordstart": "12月29日"
		}, {
			"id": "53752",
			"title": "狼爪品牌专场",
			"watchword": "2件8折",
			"image": "http://i.okaybuy.cn/images/multipic/new/201612/63/63931bbd79d3b91acae2b2e0acde1597.jpg",
			"slogan": "年末清仓特惠",
			"discount": "2件8折",
			"discount_word": "",
			"starttime": "12/29/2016 10:00:01",
			"endtime": "01/03/2017 09:59:59",
			"nowtime": "12/29/2016 21:49:04",
			"link": "/outlets/show/53752",
			"isnew": 1,
			"islastday": 0,
			"pic_word": "12月29日-01月03日",
			"pic_wordstart": "12月29日"
		}
	]
	,[
		{
			"id": "53916",
			"title": "木村井泓原宿专场",
			"watchword": "",
			"image": "http://i.okaybuy.cn/images/multipic/new/201612/84/84f64a34131f0c44e702f694d0d7b368.jpg",
			"slogan": "品牌风尚 潮流经典",
			"discount": "49元起",
			"discount_word": "",
			"starttime": "12/29/2016 10:00:00",
			"endtime": "01/05/2017 09:59:59",
			"nowtime": "12/29/2016 21:50:19",
			"link": "/outlets/show/53916",
			"isnew": 1,
			"islastday": 0,
			"pic_word": "12月29日-01月05日",
			"pic_wordstart": "12月29日"
		}, {
			"id": "53827",
			"title": "杰曼妮专场",
			"watchword": "",
			"image": "http://i.okaybuy.cn/images/multipic/new/201612/fa/faca4055ccd5d4cfdc3fc2d1eb31ba57.jpg",
			"slogan": "寒意渐浓 温暖随行",
			"discount": "满69减10元",
			"discount_word": "",
			"starttime": "12/28/2016 10:00:00",
			"endtime": "01/04/2017 09:59:59",
			"nowtime": "12/29/2016 21:50:19",
			"link": "/outlets/show/53827",
			"isnew": 0,
			"islastday": 0,
			"pic_word": "12月28日-01月04日",
			"pic_wordstart": "12月28日"
		}, {
			"id": "53826",
			"title": "啄木鸟专场",
			"watchword": "",
			"image": "http://i.okaybuy.cn/images/multipic/new/201612/5f/5fe7b0ba28b1da1b11863141675f563a.jpg",
			"slogan": "限时特惠",
			"discount": "29元起",
			"discount_word": "",
			"starttime": "12/28/2016 10:00:00",
			"endtime": "01/04/2017 09:59:59",
			"nowtime": "12/29/2016 21:50:19",
			"link": "/outlets/show/53826",
			"isnew": 0,
			"islastday": 0,
			"pic_word": "12月28日-01月04日",
			"pic_wordstart": "12月28日"
		}, {
			"id": "53713",
			"title": "威廉凯特专场",
			"watchword": "满99减20 满199减40 满299减80",
			"image": "http://i.okaybuy.cn/images/multipic/new/201612/0d/0d41a325ff172e1eb4c34830bbd00226.jpg",
			"slogan": "暖心配件年终盛宴",
			"discount": "满299减80",
			"discount_word": "",
			"starttime": "12/27/2016 10:00:00",
			"endtime": "12/31/2016 09:59:59",
			"nowtime": "12/29/2016 21:50:19",
			"link": "/outlets/show/53713",
			"isnew": 0,
			"islastday": 0,
			"pic_word": "12月27日-12月31日",
			"pic_wordstart": "12月27日"
		}, {
			"id": "53720",
			"title": "卡拉羊箱包专场",
			"watchword": "“袋”爱回家，卡拉羊专场68元起",
			"image": "http://i.okaybuy.cn/images/multipic/new/201612/65/6523356627ef66cbb8ccdc0ddae88838.jpg",
			"slogan": "“袋”爱回家",
			"discount": "68元起",
			"discount_word": "",
			"starttime": "12/27/2016 10:00:00",
			"endtime": "01/03/2017 09:59:59",
			"nowtime": "12/29/2016 21:50:19",
			"link": "/outlets/show/53720",
			"isnew": 0,
			"islastday": 0,
			"pic_word": "12月27日-01月03日",
			"pic_wordstart": "12月27日"
		}, {
			"id": "53712",
			"title": "cottonpop专场",
			"watchword": "",
			"image": "http://i.okaybuy.cn/images/multipic/new/201612/bd/bd5755165ae9762e83b8be7e70c04a45.jpg",
			"slogan": "舒适棉袜",
			"discount": "12元起",
			"discount_word": "",
			"starttime": "12/26/2016 10:00:00",
			"endtime": "01/02/2017 09:59:59",
			"nowtime": "12/29/2016 21:50:19",
			"link": "/outlets/show/53712",
			"isnew": 0,
			"islastday": 0,
			"pic_word": "12月26日-01月02日",
			"pic_wordstart": "12月26日"
		}, {
			"id": "53692",
			"title": "swisswin专场",
			"watchword": "",
			"image": "http://i.okaybuy.cn/images/multipic/new/201612/53/53781afcc4d944b988a22ed315b84c8c.jpg",
			"slogan": "品质背包",
			"discount": "68元起",
			"discount_word": "",
			"starttime": "12/26/2016 10:00:00",
			"endtime": "01/02/2017 09:59:59",
			"nowtime": "12/29/2016 21:50:19",
			"link": "/outlets/show/53692",
			"isnew": 0,
			"islastday": 0,
			"pic_word": "12月26日-01月02日",
			"pic_wordstart": "12月26日"
		}, {
			"id": "53566",
			"title": "波斯丹顿专场",
			"watchword": "",
			"image": "http://i.okaybuy.cn/images/multipic/new/201612/16/16439b4d184728877e5f1fa808026603.jpg",
			"slogan": "时尚背包",
			"discount": "99元减10 上不封顶",
			"discount_word": "",
			"starttime": "12/25/2016 10:00:00",
			"endtime": "01/01/2017 09:59:59",
			"nowtime": "12/29/2016 21:50:19",
			"link": "/outlets/show/53566",
			"isnew": 0,
			"islastday": 0,
			"pic_word": "12月25日-01月01日",
			"pic_wordstart": "12月25日"
		}, {
			"id": "53614",
			"title": "凯蒙特专场",
			"watchword": "满199减30元 满299减50元 满499减100元",
			"image": "http://i.okaybuy.cn/images/multipic/new/201612/61/61db564db279156d88cb46945ebacf0e.jpg",
			"slogan": "精品帽子",
			"discount": "满499减100元",
			"discount_word": "",
			"starttime": "12/25/2016 10:00:00",
			"endtime": "01/01/2017 09:59:59",
			"nowtime": "12/29/2016 21:50:19",
			"link": "/outlets/show/53614",
			"isnew": 0,
			"islastday": 0,
			"pic_word": "12月25日-01月01日",
			"pic_wordstart": "12月25日"
		}, {
			"id": "53545",
			"title": "丹爵专场",
			"watchword": "",
			"image": "http://i.okaybuy.cn/images/multipic/new/201612/aa/aa9466331bab42c99a5e181aa42fe0c7.jpg",
			"slogan": "狂欢圣诞季",
			"discount": "满100减10 上不封顶",
			"discount_word": "",
			"starttime": "12/24/2016 10:00:00",
			"endtime": "12/31/2016 09:59:59",
			"nowtime": "12/29/2016 21:50:19",
			"link": "/outlets/show/53545",
			"isnew": 0,
			"islastday": 0,
			"pic_word": "12月24日-12月31日",
			"pic_wordstart": "12月24日"
		}, {
			"id": "53678",
			"title": "宾尼亚专场",
			"watchword": "满89元减10元 满259元减30元 满358元减50元",
			"image": "http://i.okaybuy.cn/images/multipic/new/201612/56/565e6d4c2ac52733966c8b1988295660.jpg",
			"slogan": "圣诞狂欢",
			"discount": "满358元减50元",
			"discount_word": "",
			"starttime": "12/24/2016 10:00:00",
			"endtime": "12/31/2016 09:59:59",
			"nowtime": "12/29/2016 21:50:19",
			"link": "/outlets/show/53678",
			"isnew": 0,
			"islastday": 0,
			"pic_word": "12月24日-12月31日",
			"pic_wordstart": "12月24日"
		}, {
			"id": "53616",
			"title": "包配特惠专场",
			"watchword": "",
			"image": "http://i.okaybuy.cn/images/multipic/new/201612/e3/e3060892ea39965984f51f3c639750bc.jpg",
			"slogan": "休闲潮流 时尚经典",
			"discount": "149元起",
			"discount_word": "",
			"starttime": "12/23/2016 10:00:00",
			"endtime": "12/30/2016 09:59:59",
			"nowtime": "12/29/2016 21:50:19",
			"link": "/outlets/show/53616",
			"isnew": 0,
			"islastday": 1,
			"pic_word": "12月23日-12月30日",
			"pic_wordstart": "12月23日"
		}, {
			"id": "53543",
			"title": "梦娜米露专场",
			"watchword": "",
			"image": "http://i.okaybuy.cn/images/multipic/new/201612/04/045bfd60566db15b02b53a37520b8e0e.jpg",
			"slogan": "时尚优雅范",
			"discount": "一件9折 两件8.5折",
			"discount_word": "",
			"starttime": "12/23/2016 10:00:00",
			"endtime": "12/30/2016 09:59:59",
			"nowtime": "12/29/2016 21:50:19",
			"link": "/outlets/show/53543",
			"isnew": 0,
			"islastday": 1,
			"pic_word": "12月23日-12月30日",
			"pic_wordstart": "12月23日"
		}, {
			"id": "53942",
			"title": "途斯卡洛拉专场",
			"watchword": "全场满259减30 359减50 459减100",
			"image": "http://i.okaybuy.cn/images/multipic/new/201612/f7/f775068c9f7509d6a397a9fb0c5f4e44.jpg",
			"slogan": "岁末迎新 年终钜惠",
			"discount": "满459减100元",
			"discount_word": "",
			"starttime": "12/30/2016 10:00:00",
			"endtime": "01/06/2017 09:59:59",
			"nowtime": "12/29/2016 21:50:19",
			"link": "/outlets/show/53942",
			"isnew": -1,
			"islastday": 0,
			"pic_word": "12月30日-01月06日",
			"pic_wordstart": "12月30日"
		}, {
			"id": "53943",
			"title": "优臣品专场",
			"watchword": "",
			"image": "http://i.okaybuy.cn/images/multipic/new/201612/4a/4a90f07386c659940bdca917e5132a27.jpg",
			"slogan": "时尚男女袜",
			"discount": "满69减30元",
			"discount_word": "",
			"starttime": "12/30/2016 10:00:00",
			"endtime": "01/06/2017 09:59:59",
			"nowtime": "12/29/2016 21:50:19",
			"link": "/outlets/show/53943",
			"isnew": -1,
			"islastday": 0,
			"pic_word": "12月30日-01月06日",
			"pic_wordstart": "12月30日"
		}, {
			"id": "53985",
			"title": "潮包专场",
			"watchword": "休闲百搭",
			"image": "http://i.okaybuy.cn/images/multipic/new/201612/64/64e65898b479436f3947df996c98c636.jpg",
			"slogan": "当红潮包上新季",
			"discount": "479元封顶",
			"discount_word": "",
			"starttime": "12/30/2016 10:00:00",
			"endtime": "01/03/2017 09:59:59",
			"nowtime": "12/29/2016 21:50:19",
			"link": "/outlets/show/53985",
			"isnew": -1,
			"islastday": 0,
			"pic_word": "12月30日-01月03日",
			"pic_wordstart": "12月30日"
		}
	],[
		{
			"id": "53915",
			"title": "jeep童鞋专场",
			"watchword": "159元减10元 满259元减30元 满399元减50元",
			"image": "http://i.okaybuy.cn/images/multipic/new/201612/13/136f84e02dfd28ef20a9b115cc1938ca.jpg",
			"slogan": "轻柔灵动 尽享舒适",
			"discount": "满399元减50元",
			"discount_word": "",
			"starttime": "12/29/2016 10:00:00",
			"endtime": "01/05/2017 09:59:59",
			"nowtime": "12/29/2016 21:50:49",
			"link": "/outlets/show/53915",
			"isnew": 1,
			"islastday": 0,
			"pic_word": "12月29日-01月05日",
			"pic_wordstart": "12月29日"
		}, {
			"id": "53693",
			"title": "迪士尼&小熊维尼专场",
			"watchword": "满129元减10元 满199元减30元 满359元减50元",
			"image": "http://i.okaybuy.cn/images/multipic/new/201612/40/408b5d7fae7c76efe43b02b01ceb90a9.jpg",
			"slogan": "精品童鞋",
			"discount": "满359元减50",
			"discount_word": "",
			"starttime": "12/26/2016 10:00:00",
			"endtime": "01/02/2017 09:59:59",
			"nowtime": "12/29/2016 21:50:49",
			"link": "/outlets/show/53693",
			"isnew": 0,
			"islastday": 0,
			"pic_word": "12月26日-01月02日",
			"pic_wordstart": "12月26日"
		}, {
			"id": "53711",
			"title": "童鞋专场",
			"watchword": "",
			"image": "http://i.okaybuy.cn/images/multipic/new/201612/31/3101ef749ec38a7963e59bf1f4e2102f.jpg",
			"slogan": "精品童鞋",
			"discount": "3折起",
			"discount_word": "",
			"starttime": "12/25/2016 10:00:00",
			"endtime": "01/01/2017 09:59:59",
			"nowtime": "12/29/2016 21:50:49",
			"link": "/outlets/show/53711",
			"isnew": 0,
			"islastday": 0,
			"pic_word": "12月25日-01月01日",
			"pic_wordstart": "12月25日"
		}, {
			"id": "53708",
			"title": "童装专场",
			"watchword": "",
			"image": "http://i.okaybuy.cn/images/multipic/new/201611/ca/cada3818e406dd6a557fcfc0230b4092.jpg",
			"slogan": "精品童装",
			"discount": "3折起",
			"discount_word": "",
			"starttime": "12/25/2016 10:00:00",
			"endtime": "01/01/2017 09:59:59",
			"nowtime": "12/29/2016 21:50:49",
			"link": "/outlets/show/53708",
			"isnew": 0,
			"islastday": 0,
			"pic_word": "12月25日-01月01日",
			"pic_wordstart": "12月25日"
		}, {
			"id": "53717",
			"title": "迪尔马奇专场",
			"watchword": "全场2件8折，三件7折",
			"image": "http://i.okaybuy.cn/images/multipic/new/201612/31/3194c494d911021668fae82d2843fced.jpg",
			"slogan": "精品男装",
			"discount": "2件8折 3件7折",
			"discount_word": "",
			"starttime": "12/27/2016 10:00:00",
			"endtime": "01/02/2017 09:59:59",
			"nowtime": "12/29/2016 21:51:20",
			"link": "/outlets/show/53717",
			"isnew": 0,
			"islastday": 0,
			"pic_word": "12月27日-01月02日",
			"pic_wordstart": "12月27日"
		}, {
			"id": "53720",
			"title": "卡拉羊箱包专场",
			"watchword": "“袋”爱回家，卡拉羊专场68元起",
			"image": "http://i.okaybuy.cn/images/multipic/new/201612/65/6523356627ef66cbb8ccdc0ddae88838.jpg",
			"slogan": "“袋”爱回家",
			"discount": "68元起",
			"discount_word": "",
			"starttime": "12/27/2016 10:00:00",
			"endtime": "01/03/2017 09:59:59",
			"nowtime": "12/29/2016 21:51:20",
			"link": "/outlets/show/53720",
			"isnew": 0,
			"islastday": 0,
			"pic_word": "12月27日-01月03日",
			"pic_wordstart": "12月27日"
		}, {
			"id": "53691",
			"title": "富贵鸟专场",
			"watchword": "满99减10 满199满30 满299满50",
			"image": "http://i.okaybuy.cn/images/multipic/new/201612/da/da3c1aede32a41aa4eb23fc14338f96a.jpg",
			"slogan": "时尚经典 温暖舒适",
			"discount": "满299满50元",
			"discount_word": "",
			"starttime": "12/26/2016 10:00:00",
			"endtime": "12/30/2016 09:59:59",
			"nowtime": "12/29/2016 21:51:20",
			"link": "/outlets/show/53691",
			"isnew": 0,
			"islastday": 1,
			"pic_word": "12月26日-12月30日",
			"pic_wordstart": "12月26日"
		}, {
			"id": "53617",
			"title": "康莉女靴专场",
			"watchword": "满299减80 满598减150",
			"image": "http://i.okaybuy.cn/images/multipic/new/201612/d2/d222621214fc0e9da56529b78073c6fd.jpg",
			"slogan": "时尚潮流冬季女鞋",
			"discount": "满598减150",
			"discount_word": "",
			"starttime": "12/26/2016 10:00:00",
			"endtime": "12/30/2016 09:59:59",
			"nowtime": "12/29/2016 21:51:20",
			"link": "/outlets/show/53617",
			"isnew": 0,
			"islastday": 1,
			"pic_word": "12月26日-12月30日",
			"pic_wordstart": "12月26日"
		}, {
			"id": "53680",
			"title": "星期六女鞋专场",
			"watchword": "",
			"image": "http://i.okaybuy.cn/images/multipic/new/201612/5f/5f9c60c17f0566aaa4e623b509274af6.jpg",
			"slogan": "靓丽舒适美鞋",
			"discount": "下单立减50元",
			"discount_word": "",
			"starttime": "12/26/2016 10:00:00",
			"endtime": "12/30/2016 09:59:59",
			"nowtime": "12/29/2016 21:51:20",
			"link": "/outlets/show/53680",
			"isnew": 0,
			"islastday": 1,
			"pic_word": "12月26日-12月30日",
			"pic_wordstart": "12月26日"
		}, {
			"id": "53689",
			"title": "Hardly Ever\\'s专场",
			"watchword": "",
			"image": "http://i.okaybuy.cn/images/multipic/new/201612/6b/6bea6714ceb566ea5f5a8267e6c1c16a.jpg",
			"slogan": "时尚出型",
			"discount": "折上7.5折",
			"discount_word": "",
			"starttime": "12/26/2016 10:00:00",
			"endtime": "01/02/2017 09:59:59",
			"nowtime": "12/29/2016 21:51:20",
			"link": "/outlets/show/53689",
			"isnew": 0,
			"islastday": 0,
			"pic_word": "12月26日-01月02日",
			"pic_wordstart": "12月26日"
		}, {
			"id": "53712",
			"title": "cottonpop专场",
			"watchword": "",
			"image": "http://i.okaybuy.cn/images/multipic/new/201612/bd/bd5755165ae9762e83b8be7e70c04a45.jpg",
			"slogan": "舒适棉袜",
			"discount": "12元起",
			"discount_word": "",
			"starttime": "12/26/2016 10:00:00",
			"endtime": "01/02/2017 09:59:59",
			"nowtime": "12/29/2016 21:51:20",
			"link": "/outlets/show/53712",
			"isnew": 0,
			"islastday": 0,
			"pic_word": "12月26日-01月02日",
			"pic_wordstart": "12月26日"
		}
	],[
		{
			"id": "53757",
			"title": "波司登棉羽专场",
			"watchword": "",
			"image": "http://i.okaybuy.cn/images/multipic/new/201612/40/4030e6bb26607c80219e93c6b1759a2b.jpg",
			"slogan": "羽绒保暖 贴心舒适",
			"discount": "下单立享8折",
			"discount_word": "",
			"starttime": "12/27/2016 10:00:00",
			"endtime": "12/30/2016 09:59:59",
			"nowtime": "12/29/2016 21:51:20",
			"link": "/outlets/show/53757",
			"isnew": 0,
			"islastday": 1,
			"pic_word": "12月27日-12月30日",
			"pic_wordstart": "12月27日"
		}, {
			"id": "53755",
			"title": "Levis专场",
			"watchword": "",
			"image": "http://i.okaybuy.cn/images/multipic/new/201612/74/7442440f44afed456a016a8f8c27924a.jpg",
			"slogan": "潮流新主义",
			"discount": "一件9折 两件8.5折",
			"discount_word": "",
			"starttime": "12/27/2016 10:00:00",
			"endtime": "12/30/2016 09:59:59",
			"nowtime": "12/29/2016 21:51:20",
			"link": "/outlets/show/53755",
			"isnew": 0,
			"islastday": 1,
			"pic_word": "12月27日-12月30日",
			"pic_wordstart": "12月27日"
		}, {
			"id": "53756",
			"title": "Lee专场",
			"watchword": "",
			"image": "http://i.okaybuy.cn/images/multipic/new/201612/60/6004dd4dc849fc3d0e52a0d6eefadd98.jpg",
			"slogan": "牛仔经典 好奇不灭",
			"discount": "一件9折两件8.5折",
			"discount_word": "",
			"starttime": "12/27/2016 10:00:00",
			"endtime": "12/30/2016 09:59:59",
			"nowtime": "12/29/2016 21:51:20",
			"link": "/outlets/show/53756",
			"isnew": 0,
			"islastday": 1,
			"pic_word": "12月27日-12月30日",
			"pic_wordstart": "12月27日"
		}, {
			"id": "53700",
			"title": "鸿星尔克专场",
			"watchword": "",
			"image": "http://i.okaybuy.cn/images/multipic/new/201611/c3/c3a7240f02a4a8cff0e67edd348cf20a.jpg",
			"slogan": "舒适 休闲 经典",
			"discount": "66元起",
			"discount_word": "",
			"starttime": "12/27/2016 10:00:00",
			"endtime": "01/03/2017 09:59:59",
			"nowtime": "12/29/2016 21:51:20",
			"link": "/outlets/show/53700",
			"isnew": 0,
			"islastday": 0,
			"pic_word": "12月27日-01月03日",
			"pic_wordstart": "12月27日"
		}, {
			"id": "53738",
			"title": "骆驼牌专场",
			"watchword": "",
			"image": "http://i.okaybuy.cn/images/multipic/new/201612/56/564b8fb1aa8ccfa5850834191653cf8b.jpg",
			"slogan": "休闲经典男女鞋",
			"discount": "99元起",
			"discount_word": "",
			"starttime": "12/27/2016 10:00:00",
			"endtime": "01/02/2017 09:59:59",
			"nowtime": "12/29/2016 21:51:20",
			"link": "/outlets/show/53738",
			"isnew": 0,
			"islastday": 0,
			"pic_word": "12月27日-01月02日",
			"pic_wordstart": "12月27日"
		}, {
			"id": "53740",
			"title": "悍途专场",
			"watchword": "",
			"image": "http://i.okaybuy.cn/images/multipic/new/201612/4a/4ad000f794c00c7de96feefd83da5ff9.jpg",
			"slogan": "畅行户外",
			"discount": "1折起",
			"discount_word": "",
			"starttime": "12/27/2016 10:00:00",
			"endtime": "01/03/2017 09:59:59",
			"nowtime": "12/29/2016 21:51:20",
			"link": "/outlets/show/53740",
			"isnew": 0,
			"islastday": 0,
			"pic_word": "12月27日-01月03日",
			"pic_wordstart": "12月27日"
		}, {
			"id": "53759",
			"title": "森马专场",
			"watchword": "99减20元 159减40元",
			"image": "http://i.okaybuy.cn/images/multipic/new/201612/98/983a6129aa9095d2f7db4c3d4f03596c.jpg",
			"slogan": "冬季清仓",
			"discount": "159减40元",
			"discount_word": "",
			"starttime": "12/27/2016 10:00:00",
			"endtime": "12/30/2016 09:59:59",
			"nowtime": "12/29/2016 21:51:20",
			"link": "/outlets/show/53759",
			"isnew": 0,
			"islastday": 1,
			"pic_word": "12月27日-12月30日",
			"pic_wordstart": "12月27日"
		}, {
			"id": "53760",
			"title": "dickies专场",
			"watchword": "",
			"image": "http://i.okaybuy.cn/images/multipic/new/201612/a5/a5c0e7dfac7b32b7543c545fc3d8fc9d.jpg",
			"slogan": "冬季清仓",
			"discount": "59元起 两件再8折",
			"discount_word": "",
			"starttime": "12/27/2016 10:00:00",
			"endtime": "12/30/2016 09:59:59",
			"nowtime": "12/29/2016 21:51:20",
			"link": "/outlets/show/53760",
			"isnew": 0,
			"islastday": 1,
			"pic_word": "12月27日-12月30日",
			"pic_wordstart": "12月27日"
		}, {
			"id": "53747",
			"title": "美特斯邦威专场",
			"watchword": "",
			"image": "http://i.okaybuy.cn/images/multipic/new/201612/11/11c0ae96bb0b084ae5c321cf0e122cd8.jpg",
			"slogan": "休闲舒适 时尚经典",
			"discount": "棉羽169封顶",
			"discount_word": "",
			"starttime": "12/27/2016 10:00:00",
			"endtime": "12/30/2016 09:59:59",
			"nowtime": "12/29/2016 21:51:20",
			"link": "/outlets/show/53747",
			"isnew": 0,
			"islastday": 1,
			"pic_word": "12月27日-12月30日",
			"pic_wordstart": "12月27日"
		}, {
			"id": "53749",
			"title": "女装特惠专场",
			"watchword": "",
			"image": "http://i.okaybuy.cn/images/multipic/new/201612/54/54bb07d2385b47ac12277d08e0fe1514.jpg",
			"slogan": "时尚女装",
			"discount": "100元4件",
			"discount_word": "",
			"starttime": "12/27/2016 10:00:00",
			"endtime": "01/05/2017 09:59:59",
			"nowtime": "12/29/2016 21:51:20",
			"link": "/outlets/show/53749",
			"isnew": 0,
			"islastday": 0,
			"pic_word": "12月27日-01月05日",
			"pic_wordstart": "12月27日"
		}, {
			"id": "53745",
			"title": "CROCS专场",
			"watchword": "",
			"image": "http://i.okaybuy.cn/images/multipic/new/201612/8b/8b205ff662933d2ba79fce2ea7aa98b9.jpg",
			"slogan": "舒适 休闲 经典",
			"discount": "99元起",
			"discount_word": "",
			"starttime": "12/27/2016 10:00:00",
			"endtime": "12/30/2016 09:59:59",
			"nowtime": "12/29/2016 21:51:20",
			"link": "/outlets/show/53745",
			"isnew": 0,
			"islastday": 1,
			"pic_word": "12月27日-12月30日",
			"pic_wordstart": "12月27日"
		}, {
			"id": "53742",
			"title": "户外断码清仓专场",
			"watchword": "",
			"image": "http://i.okaybuy.cn/images/multipic/new/201611/94/941ad1928c930aa81c3e1002c83afd8f.jpg",
			"slogan": "断码捡漏 超值之选",
			"discount": "1折起",
			"discount_word": "",
			"starttime": "12/27/2016 10:00:00",
			"endtime": "01/03/2017 09:59:59",
			"nowtime": "12/29/2016 21:51:20",
			"link": "/outlets/show/53742",
			"isnew": 0,
			"islastday": 0,
			"pic_word": "12月27日-01月03日",
			"pic_wordstart": "12月27日"
		}, {
			"id": "53741",
			"title": "DICKIES工装鞋专场",
			"watchword": "",
			"image": "http://i.okaybuy.cn/images/multipic/new/201611/d1/d16579d4dbd2bae79e3dcc66b8e3bb16.jpg",
			"slogan": "元旦特惠",
			"discount": "89起 399封顶",
			"discount_word": "",
			"starttime": "12/27/2016 10:00:00",
			"endtime": "12/30/2016 09:59:59",
			"nowtime": "12/29/2016 21:51:20",
			"link": "/outlets/show/53741",
			"isnew": 0,
			"islastday": 1,
			"pic_word": "12月27日-12月30日",
			"pic_wordstart": "12月27日"
		}, {
			"id": "53713",
			"title": "威廉凯特专场",
			"watchword": "满99减20 满199减40 满299减80",
			"image": "http://i.okaybuy.cn/images/multipic/new/201612/0d/0d41a325ff172e1eb4c34830bbd00226.jpg",
			"slogan": "暖心配件年终盛宴",
			"discount": "满299减80",
			"discount_word": "",
			"starttime": "12/27/2016 10:00:00",
			"endtime": "12/31/2016 09:59:59",
			"nowtime": "12/29/2016 21:51:20",
			"link": "/outlets/show/53713",
			"isnew": 0,
			"islastday": 0,
			"pic_word": "12月27日-12月31日",
			"pic_wordstart": "12月27日"
		}, {
			"id": "53715",
			"title": "海德&弗格力专场",
			"watchword": "",
			"image": "http://i.okaybuy.cn/images/multipic/new/201612/e2/e2c05546511e6d012bbf3fec0f73d360.jpg",
			"slogan": "精品球鞋球拍",
			"discount": "1件9折 2件8折",
			"discount_word": "",
			"starttime": "12/27/2016 10:00:00",
			"endtime": "01/03/2017 09:59:59",
			"nowtime": "12/29/2016 21:51:20",
			"link": "/outlets/show/53715",
			"isnew": 0,
			"islastday": 0,
			"pic_word": "12月27日-01月03日",
			"pic_wordstart": "12月27日"
		}, {
			"id": "53716",
			"title": "银卫士&维尔雅&贴身高手专场",
			"watchword": "满69减10元",
			"image": "http://i.okaybuy.cn/images/multipic/new/201612/36/369096b555b67b41de554fd3852b7c09.jpg",
			"slogan": "内衣必备",
			"discount": "满69减10元",
			"discount_word": "",
			"starttime": "12/27/2016 10:00:00",
			"endtime": "01/03/2017 09:59:59",
			"nowtime": "12/29/2016 21:51:20",
			"link": "/outlets/show/53716",
			"isnew": 0,
			"islastday": 0,
			"pic_word": "12月27日-01月03日",
			"pic_wordstart": "12月27日"
		}
	]
]